walrus.py
python_walrus-0.1.4.dist-info/LICENSE
python_walrus-0.1.4.dist-info/METADATA
python_walrus-0.1.4.dist-info/WHEEL
python_walrus-0.1.4.dist-info/entry_points.txt
python_walrus-0.1.4.dist-info/top_level.txt
python_walrus-0.1.4.dist-info/zip-safe
python_walrus-0.1.4.dist-info/RECORD
