Metadata-Version: 2.1
Name: python-walrus
Version: 0.1.4
Summary: Back-port compiler for Python 3.8 assignment expressions.
Home-page: https://github.com/pybpc/walrus
Author: Jarry Shaw
Author-email: jarryshaw@icloud.com
License: Apache Software License
Keywords: walrus operator,assignment expression,back-port compiler
Platform: UNKNOWN
Classifier: Development Status :: 4 - Beta
Classifier: Intended Audience :: Developers
Classifier: License :: OSI Approved :: MIT License
Classifier: Natural Language :: English
Classifier: Operating System :: OS Independent
Classifier: Programming Language :: Python
Classifier: Programming Language :: Python :: 3.3
Classifier: Programming Language :: Python :: 3.4
Classifier: Programming Language :: Python :: 3.5
Classifier: Programming Language :: Python :: 3.6
Classifier: Programming Language :: Python :: 3.7
Classifier: Programming Language :: Python :: 3.8
Classifier: Programming Language :: Python :: 3 :: Only
Classifier: Topic :: Software Development
Classifier: Topic :: Utilities
Requires-Python: >=3.3
Requires-Dist: parso (>=0.6.0)
Requires-Dist: tbtrim (>=0.2.1)
Requires-Dist: bpc-utils
